LICENSE.txt
MANIFEST.in
README.rst
setup.py
teslatoken.py
teslatoken.egg-info/PKG-INFO
teslatoken.egg-info/SOURCES.txt
teslatoken.egg-info/dependency_links.txt
teslatoken.egg-info/entry_points.txt
teslatoken.egg-info/requires.txt
teslatoken.egg-info/top_level.txt