Metadata-Version: 1.0
Name: teslatoken
Version: 0.1.3
Summary: Tool to create authorization tokens for Tesla cars.
Home-page: https://github.com/eric1980/teslatoken
Author: Eric Fornstedt
Author-email: eric.fornstedt@gmail.com
License: MIT License
